[
  {
    "locale": "en"
  },
  {
    "key": "s",
    "category": "time",
    "mappings": {
      "default": {
        "default": "second"
      }
    },
    "si": true,
    "names": [
      "s"
    ]
  },
  {
    "key": "″",
    "category": "time",
    "mappings": {
      "default": {
        "default": "second"
      }
    },
    "names": [
      "″"
    ]
  },
  {
    "key": "min",
    "category": "time",
    "mappings": {
      "default": {
        "default": "minute"
      }
    },
    "names": [
      "min",
      "′"
    ]
  },
  {
    "key": "°",
    "category": "time",
    "mappings": {
      "default": {
        "default": "degree"
      }
    },
    "names": [
      "°"
    ]
  },
  {
    "key": "h",
    "category": "time",
    "mappings": {
      "default": {
        "default": "hour"
      }
    },
    "names": [
      "h",
      "hr"
    ]
  }
]
