[
  {
    "locale": "nn"
  },
  {
    "key": "03D0",
    "category": "Ll",
    "mappings": {
      "default": {
        "default": "beta"
      }
    }
  },
  {
    "key": "03D7",
    "category": "Ll",
    "mappings": {
      "default": {
        "default": "kai"
      }
    }
  },
  {
    "key": "03F6",
    "category": "Sm",
    "mappings": {
      "default": {
        "default": "omvendt epsilon"
      }
    }
  },
  {
    "key": "1D7CA",
    "category": "Lu",
    "mappings": {
      "default": {
        "default": "feit hevet digamma"
      }
    }
  },
  {
    "key": "1D7CB",
    "category": "Ll",
    "mappings": {
      "default": {
        "default": "feit digamma"
      }
    }
  }
]
