[
  {
    "locale": "it"
  },
  {
    "key": "sq",
    "mappings": {
      "default": {
        "plural": "quadrati",
        "default": "quadrato"
      }
    }
  },
  {
    "key": "sq inch",
    "mappings": {
      "default": {
        "plural": "pollici quadrati",
        "default": "pollice quadrato"
      }
    }
  },
  {
    "key": "sq rd",
    "mappings": {
      "default": {
        "plural": "pertiche quadrati",
        "default": "pertica quadrata"
      }
    }
  },
  {
    "key": "sq ft",
    "mappings": {
      "default": {
        "plural": "piedi quadrati",
        "default": "piede quadrato"
      }
    }
  },
  {
    "key": "sq yd",
    "mappings": {
      "default": {
        "plural": "iarde quadrate",
        "default": "iarda quadrata"
      }
    }
  },
  {
    "key": "sq mi",
    "mappings": {
      "default": {
        "plural": "miglia quadrate",
        "default": "miglio quadrato"
      }
    }
  },
  {
    "key": "acr",
    "mappings": {
      "default": {
        "plural": "acri",
        "default": "acro"
      }
    }
  },
  {
    "key": "ha",
    "mappings": {
      "default": {
        "plural": "ettari",
        "default": "ettaro"
      }
    }
  }
]
